tsv_tree/__init__.py
tsv_tree/keys_file.py
tsv_tree/map_file.py
tsv_tree/tsv_file.py
tsv_tree/util.py
tsv_tree/zip_file.py
tsv_tree-0.1.0.dist-info/licenses/LICENSE
tsv_tree-0.1.0.dist-info/METADATA
tsv_tree-0.1.0.dist-info/WHEEL
tsv_tree-0.1.0.dist-info/top_level.txt
tsv_tree-0.1.0.dist-info/RECORD
