Metadata-Version: 2.4
Name: tsv_tree
Version: 0.1.0
Summary: Library for tsv_tree file format handling
Author-email: Arthur Gouhier <ajgouhier@gmail.com>
License-Expression: MIT
Project-URL: Repository, https://github.com/ajgouhier/tsv_tree
Requires-Python: >=3.8
License-File: LICENSE
Requires-Dist: zstd>=1.5
Dynamic: license-file
